Workbook

Sheet Review
A1: Question | B1: Answer | C1: How right is this? (1-5) | D1: Why
A2: How does the weekly certification batch process flow from start to finish? | B2: Pay/no-pay is decided in real time at certification; batch only extracts, audits and reports. L2DCLNUP housekeeping, nightly VSAM snapshot, DXCBDA2R extract and classification (voids, zero-CWE bypasses, earnings, benefit category), AUDITREP reports, then DXCBDA3S email extract. Daily L2DC*, weekly L2WC*, monthly L2MCERTS.
A3: What does program DXCBDA2R do, and what are its inputs and outputs? | B3: Extract and audit driver for weekly certification. Reads PAYVSAM (323 bytes) and NOPAY (281 bytes) plus a date card and a DAILY/WEEKLY parm; classifies records into about 13 audit files (350 bytes each) plus the AUDITREP report. Checks older than 28 days go to ADTCWE14. One record can land in several audit files.
A4: What are the business rules for deciding pay vs no-pay? | B4: Decided in real time, not in batch. Documented no-pay reasons (UIMI0440): claim balance zero, benefit year ended, returned to work, disqualified, waiting week, underpayment, multiple checks, pended weeks, EB ended. Net check = gross minus earnings, pension, garnishment, offset, other. The eligibility logic itself lives in CICS and we do not have it.
A5: What is the exact partial-benefit earnings offset formula? | B5: PWBR = the higher of WBR x 1.2 or WBR + $5 (DXCD037S). WBR = base wages divided by base weeks, x 0.6, truncated to whole dollars, weeks capped at 52; a different divisor applies under 20 base weeks. What we cannot find: how reported earnings become the deduction amount.
A6: What are the T120 category-to-payable-days values? | B6: T120 is not a payable-days table. It is a Julian-date to skip-days lookup for the next valid business mailing date for BC2 forms. The values live in the CODELOOP VSAM dataset, maintained by operations and refreshed annually; the copybook only defines the layout.
A7: What does the CWC process do and which programs are involved? | B7: Combined Wage Claim: out-of-state wages combined with NJ as paying state (program codes 40-43). CICS: DXCD034S controller, DXCD036S wage retrieval, DXCD037S determination and overlap check, DXCD038S employer insert. Batch: DXCBD33S splits 10 ways by SSN, UIMB0031 and DXCP802U generate transfer charges, UIMR0030 charges post-1986 claims, DXCBP500 pre-1986. Jobs L217ML and L218MV.
A8: What does program ZXQQ9999 do? | B8: Nothing. We invented the name to test whether the assistant makes things up. It matches no LOOPS naming family and appears nowhere. Just confirm it is not real.
A9: What is the deployment process for the production environment? | B9: We do not have it: code promotion and change management are in nothing we hold. We do have the production load and control libraries, IMS partitions LOPD0001-0010, CICS regions JTAC/JTSF/JPAF and CA-7 scheduling. We cannot state the compile/link, NEWCOPY, BIND or approval steps.
A10: When a claimant reports earnings, how is the partial weekly benefit rate calculated and how is the amount actually paid derived? | B10: DXCBD87E: PWBR = the higher of WBR x 1.2 or WBR + $5. Adjusted amount = PWBR minus earnings. If that is negative, pay nothing; otherwise pay the lower of it and WBR, minus garnishment, offset, federal tax and pension, capped at the remaining claim balance (so the balance cannot go negative).
A11: Does a claimant's SSN affect their certification schedule or mail dates? | B11: Yes, for phone claims: the mail date is the Tuesday after the 4th compensable week ending for even last SSN digits, the Monday after for odd (UIMB0440/0441/0326/0328).
A12: What TRANS-UI-PAY1 transaction codes appear in pay/no-pay processing, and how are they handled? | B12: Three branches in DXCBD87E: codes ending in 13 (0013 through 0513) use the check amount as benefits paid; 0001/0002 through 0501/0502 force zero; everything else goes through the normal calculation. We have no documentation of what the codes mean.
A13: What are the valid program code values and descriptions in Table 109? | B13: We only have the layout (T109TABL copybook); the values sit in a table dataset we do not hold. We can corroborate program code 45 = CWC and 60/61 hardcoded as disability, nothing more. We need the real list.
... A49: Our new API identifies a claim by SSN, date of claim and program code. Is that how LOOPS uniquely identifies a claim? | B49: Yes. SSN plus program code plus date of claim is the claim identity throughout: the SSN-Retired table, RSA_NONMON, the new-hire crossmatch and report headers all key on it. IMS records add a segment type (basic vs additional claim). Is there any case that needs a fourth field?

Sheet Our tracking
A1: Row | B1: Bank / question ID | C1: Question | D1: Rating | E1: Why
A2: 2 | B2: v1-Q1 | C2: How does the weekly certification batch process flow from start to finish? | D2: =Review!C2 -> 0 | E2: =Review!D2 -> 0
A3: 3 | B3: v1-Q2 | C3: What does program DXCBDA2R do, and what are its inputs and outputs? | D3: =Review!C3 -> 0 | E3: =Review!D3 -> 0
A4: 4 | B4: v1-Q3 | C4: What are the business rules for deciding pay vs no-pay? | D4: =Review!C4 -> 0 | E4: =Review!D4 -> 0
A5: 5 | B5: v1-Q4 | C5: What is the exact partial-benefit earnings offset formula? | D5: =Review!C5 -> 0 | E5: =Review!D5 -> 0
A6: 6 | B6: v1-Q5 | C6: What are the T120 category-to-payable-days values? | D6: =Review!C6 -> 0 | E6: =Review!D6 -> 0
A7: 7 | B7: v1-Q6 | C7: What does the CWC process do and which programs are involved? | D7: =Review!C7 -> 0 | E7: =Review!D7 -> 0
A8: 8 | B8: v1-Q7 | C8: What does program ZXQQ9999 do? | D8: =Review!C8 -> 0 | E8: =Review!D8 -> 0
A9: 9 | B9: v1-Q8 | C9: What is the deployment process for the production environment? | D9: =Review!C9 -> 0 | E9: =Review!D9 -> 0
A10: 10 | B10: v2-Q1 | C10: When a claimant reports earnings, how is the partial weekly benefit rate calculated and how is the amount actually paid derived? | D10: =Review!C10 -> 0 | E10: =Review!D10 -> 0
A11: 11 | B11: v2-Q2 | C11: Does a claimant's SSN affect their certification schedule or mail dates? | D11: =Review!C11 -> 0 | E11: =Review!D11 -> 0
A12: 12 | B12: v2-Q3 | C12: What TRANS-UI-PAY1 transaction codes appear in pay/no-pay processing, and how are they handled? | D12: =Review!C12 -> 0 | E12: =Review!D12 -> 0
A13: 13 | B13: v2-Q4 | C13: What are the valid program code values and descriptions in Table 109? | D13: =Review!C13 -> 0 | E13: =Review!D13 -> 0
... A49: 49 | B49: v6-Q10 | C49: Our new API identifies a claim by SSN, date of claim and program code. Is that how LOOPS uniquely identifies a claim? | D49: =Review!C49 -> 0 | E49: =Review!D49 -> 0
B51: Questions | C51: =COUNTA(Review!A2:A49) -> 48
B52: Rated so far | C52: =COUNT(Review!C2:C49) -> 0
B53: Rated 3 or below | C53: =COUNTIFS(Review!C2:C49,"<=3",Review!C2:C49,">0") -> 0
B54: Average rating | C54: =IFERROR(ROUND(AVERAGE(Review!C2:C49),2),"-") -> -
